just_compose/__init__.py
just_compose/main.py
just_compose-0.2.6.dist-info/LICENSE
just_compose-0.2.6.dist-info/METADATA
just_compose-0.2.6.dist-info/WHEEL
just_compose-0.2.6.dist-info/entry_points.txt
just_compose-0.2.6.dist-info/top_level.txt
just_compose-0.2.6.dist-info/RECORD
