Metadata-Version: 2.1
Name: just-compose
Version: 0.2.6
Summary: A system for management of multiple processes
Home-page: https://github.com/richard-hajek
Author: Richard Hajek
Author-email: richard.m.hajek@gmail.com
Project-URL: Bug Tracker, https://github.com/richard-hajek
Classifier: Programming Language :: Python :: 3
Requires-Python: >=3.6
License-File: LICENSE
Requires-Dist: sh
Requires-Dist: colorama
Requires-Dist: pyyaml
